{"name":"Boidmachine","tagline":"","body":"# Boid Machine\r\nNetlight är som en konversation, om vilka vi är, vad vi gör och vart vi vill gå. **Boid – In command** pekar på friheten att alla har friheten att leda konversationen. Hur kan vi hantera ta del av denna konversationen på ett transeuropean sätt? \r\n\r\n# Boid like email! \r\nMöjligheten att skicka ett meddelande till hela Netlight, en liten grupp i taget, tycker gruppen att det är ett bra meddelande slussas det vidare till en större grupp. Till slut når de meddelanden som hela Netlight ställer sig bakom, hela Netlight. De tankar som inte är fullständigt uttänkta, saknar en vinkel eller inte passar in, filtreras på vägen och når bara en fraktion av Netlight.\r\n\r\nKonversationen på Netlight har ett brusproblem, det är dags att hitta ett sätt för att hitta signalen.","google":"","note":"Don't delete this file! It's used internally to help with page regeneration."}